fezrs/__init__.py
fezrs/base.py
fezrs/media/logo_watermark.png
fezrs/tools/__init__.py
fezrs/tools/change_detection/__inti__.py
fezrs/tools/change_detection/burn_calculator.py
fezrs/tools/change_detection/indices_calculator.py
fezrs/tools/change_detection/magdir_calculator.py
fezrs/tools/change_detection/subdiv_calculator.py
fezrs/tools/change_detection/time_calculator.py
fezrs/tools/clustering/__init__.py
fezrs/tools/clustering/kmeans_calculator.py
fezrs/tools/filters/__init__.py
fezrs/tools/filters/gaussian_calculator.py
fezrs/tools/filters/laplacian_calculator.py
fezrs/tools/filters/mean_calculator.py
fezrs/tools/filters/median_calculator.py
fezrs/tools/filters/sobel_calculator.py
fezrs/tools/glcm/__init__.py
fezrs/tools/glcm/glcm_calculator.py
fezrs/tools/hsv/__init__.py
fezrs/tools/hsv/hsv_calculator.py
fezrs/tools/hsv/irhsv_calculator.py
fezrs/tools/image_enhancement/__init__.py
fezrs/tools/image_enhancement/adaptive_calculator.py
fezrs/tools/image_enhancement/adaptive_rgb_calculator.py
fezrs/tools/image_enhancement/equalize_calculator.py
fezrs/tools/image_enhancement/equalize_rgb_calculator.py
fezrs/tools/image_enhancement/float_calculator.py
fezrs/tools/image_enhancement/gamma_calculator.py
fezrs/tools/image_enhancement/gamma_rgb_calculator.py
fezrs/tools/image_enhancement/log_adjust_calculator.py
fezrs/tools/image_enhancement/original_calculator.py
fezrs/tools/image_enhancement/original_rgb_calculator.py
fezrs/tools/image_enhancement/sigmoid_adjust_calculator.py
fezrs/tools/import_tools/__init__.py
fezrs/tools/import_tools/geoeye_calculator.py
fezrs/tools/import_tools/landsat8_calculator.py
fezrs/tools/mosaic/__init__.py
fezrs/tools/mosaic/mosaic_calculator.py
fezrs/tools/pca/__init__.py
fezrs/tools/pca/pca_calculator.py
fezrs/tools/spectral_indices/__init__.py
fezrs/tools/spectral_indices/afvi_calculator.py
fezrs/tools/spectral_indices/bi_calculator.py
fezrs/tools/spectral_indices/ndvi_calculator.py
fezrs/tools/spectral_indices/ndwi_calculator.py
fezrs-0.4.120.dist-info/licenses/LICENSE
fezrs-0.4.120.dist-info/METADATA
fezrs-0.4.120.dist-info/WHEEL
fezrs-0.4.120.dist-info/top_level.txt
fezrs-0.4.120.dist-info/RECORD
