Metadata-Version: 2.4
Name: fezrs
Version: 0.4.120
Summary: Feature Extraction and Zoning for Remote Sensing (FEZrs)
Home-page: https://github.com/FEZtool-team/FEZrs
Author: Mahdi Farmahinifarahani, Hooman Mirzaee, Mahdi Nedaee, Mohammad Hossein Kiani Fayz Abadi, Yoones Kiani Feyz Abadi, Erfan Karimzadehasl, Parsa Elmi
Author-email: aradfarahani@aol.com
Classifier: Programming Language :: Python :: 3
Classifier: License :: OSI Approved :: Apache Software License
Classifier: Operating System :: OS Independent
Requires-Python: >=3.10
License-File: LICENSE
Requires-Dist: numpy
Requires-Dist: pandas
Requires-Dist: Pillow
Requires-Dist: pydantic
Requires-Dist: matplotlib
Requires-Dist: imagecodecs
Requires-Dist: scikit-learn
Requires-Dist: scikit-image
Requires-Dist: opencv-python
Dynamic: author
Dynamic: author-email
Dynamic: classifier
Dynamic: description
Dynamic: description-content-type
Dynamic: home-page
Dynamic: license-file
Dynamic: requires-dist
Dynamic: requires-python
Dynamic: summary
